lambdahub.py
lambdahub-0.0.1.dist-info/DESCRIPTION.rst
lambdahub-0.0.1.dist-info/METADATA
lambdahub-0.0.1.dist-info/RECORD
lambdahub-0.0.1.dist-info/WHEEL
lambdahub-0.0.1.dist-info/entry_points.txt
lambdahub-0.0.1.dist-info/metadata.json
lambdahub-0.0.1.dist-info/top_level.txt
